crescience_websocket_py/__init__.py
crescience_websocket_py/check_updates.py
crescience_websocket_py/client.py
crescience_websocket_py/message.py
crescience_websocket_py-0.0.3.dist-info/METADATA
crescience_websocket_py-0.0.3.dist-info/WHEEL
crescience_websocket_py-0.0.3.dist-info/top_level.txt
crescience_websocket_py-0.0.3.dist-info/RECORD
