Metadata-Version: 2.1
Name: crescience-websocket-py
Version: 0.0.3
Summary: Websocket Client for Crescience devices
Home-page: https://github.com/cre-science/crescience-websocket-py
Author: Crescience
Author-email: development@cre.science
Keywords: pypi,crescience,python
Classifier: Development Status :: 1 - Planning
Classifier: Intended Audience :: Developers
Classifier: Programming Language :: Python :: 3
Classifier: Operating System :: Unix
Classifier: Operating System :: MacOS :: MacOS X
Classifier: Operating System :: Microsoft :: Windows
Requires-Dist: requests
